{
  "main": {
    "id": "ff8cbd0260613a7c",
    "type": "split",
    "children": [
      {
        "id": "201a5f9cea06e5d3",
        "type": "tabs",
        "children": [
          {
            "id": "b1d98da8b31d9549",
            "type": "leaf",
            "state": {
              "type": "empty",
              "state": {}
            }
          }
        ]
      }
    ],
    "direction": "vertical"
  },
  "left": {
    "id": "3ea58cb953ae5fbb",
    "type": "split",
    "children": [
      {
        "id": "fd2d7d5ef0a31673",
        "type": "tabs",
        "children": [
          {
            "id": "3d8dd75c0d1297b4",
            "type": "leaf",
            "state": {
              "type": "file-explorer",
              "state": {
                "sortOrder": "alphabetical"
              }
            }
          },
          {
            "id": "df0c118712cb16df",
            "type": "leaf",
            "state": {
              "type": "search",
              "state": {
                "query": "интегрирование по частям",
                "matchingCase": false,
                "explainSearch": false,
                "collapseAll": false,
                "extraContext": false,
                "sortOrder": "alphabetical"
              }
            }
          }
        ]
      }
    ],
    "direction": "horizontal",
    "width": 292.5024719238281
  },
  "right": {
    "id": "f52afa7cf66eb8b5",
    "type": "split",
    "children": [
      {
        "id": "0d6923e06cc96326",
        "type": "tabs",
        "children": [
          {
            "id": "9bca5c08622fa996",
            "type": "leaf",
            "state": {
              "type": "backlink",
              "state": {
                "collapseAll": false,
                "extraContext": false,
                "sortOrder": "alphabetical",
                "showSearch": false,
                "searchQuery": "",
                "backlinkCollapsed": false,
                "unlinkedCollapsed": true
              }
            }
          },
          {
            "id": "daf5f3690da5c52b",
            "type": "leaf",
            "state": {
              "type": "outgoing-link",
              "state": {
                "linksCollapsed": false,
                "unlinkedCollapsed": false
              }
            }
          },
          {
            "id": "fde3ae0e32a80ecf",
            "type": "leaf",
            "state": {
              "type": "tag",
              "state": {
                "sortOrder": "alphabeticalReverse",
                "useHierarchy": false
              }
            }
          },
          {
            "id": "e2470c350970eba2",
            "type": "leaf",
            "state": {
              "type": "outline",
              "state": {}
            }
          },
          {
            "id": "7017fa47e5650f8c",
            "type": "leaf",
            "state": {
              "type": "git-history-view",
              "state": {}
            }
          }
        ],
        "currentTab": 4
      }
    ],
    "direction": "horizontal",
    "width": 382.5,
    "collapsed": true
  },
  "left-ribbon": {
    "hiddenItems": {
      "obsidian-excalidraw-plugin:Create new drawing": false,
      "switcher:Open quick switcher": false,
      "graph:Open graph view": false,
      "templates:Insert template": false,
      "command-palette:Open command palette": false
    }
  },
  "active": "b1d98da8b31d9549",
  "lastOpenFiles": [
    "Notes/Математический анализ/Теорема об итегрировании по частям.md",
    "Dumpster/testing.md",
    "Notes/Математический анализ/Неопределенный интеграл.md",
    "Seminars/Математический анализ/2024-02-29 Семинар - Математический анализ.md",
    "Seminars/Математический анализ/2024-02-22 Семинар - Математический анализ.md",
    "Seminars/Математический анализ/2024-02-15 Семинар - Математический анализ.md",
    "Practical works/Линейная алгебра/TP 4 (линейная алгебра).md",
    "Seminars/2024-03-11 Семинар - Линейная алгебра.md",
    "Seminars/2024-03-04 Семинар - Линейная алгебра.md",
    "Practical works/Линейная алгебра/ТР 3 (линейная алгебра).md",
    "Practical works/Линейная алгебра/ТР 1 (линейная алгебра).md",
    "Seminars/2024-03-11 Семинар - История.md",
    "Practical works/Дискретная математика/ТР 1 (дискретная математика).md",
    "Practical works/Линейная алгебра/ТР 2 (линейная алгебра).md",
    "Lectures/Дискретная математика/2024-03-01 Лекция - Дискретная математика.md",
    "Lectures/Дискретная математика/2024-02-16 Лекция - Дискретная математика.md",
    "Seminars/2024-03-06 Семинар - Дискретная математика.md",
    "Seminars/Дискретная математика/2024-02-28 Семинар - Дискретная математика.md",
    "Lectures/2024-03-01 Лекция - Дискретная математика.md",
    "Practical works/Методы математического анализа/ТР 18, 19 (математический анализ) (1-ый семестр).md",
    "Seminars/Линейная алгебра/2024-02-26 Семинар - Линейная алгебра.md",
    "Practical works/Линейная алгебра",
    "Notes/Дискретная математика/Порядок группы. Порядок элемента.md",
    "Seminars/Дискретная математика/2024-02-21 Семинар - Дискретная математика.md",
    "Notes/Дискретная математика/Кольцо вычетов.md",
    "Notes/Дискретная математика/Китайская теорема об остатках.md",
    "Notes/Дискретная математика/Теорема об обратимости остатка.md",
    "Practical works/Дискретная математика",
    "Homework/Линейная алгебра",
    "Homework/English",
    "Seminars/Алгоритмика",
    "Seminars/Методы математического анализа",
    "Seminars/Дискретная математика",
    "Seminars/Линейная алгебра",
    "Seminars/История",
    "Seminars/English",
    "Untitled.canvas",
    "Images/Pasted image 20231211092631.png",
    "Images/Pasted image 20231211092421.png",
    "Images/Pasted image 20231211091936.png",
    "Images/Pasted image 20240115162255.png",
    "Pasted image 20240115162206.png",
    "Images/Pasted image 20231211092852.png",
    "Images/Pasted image 20231211092723.png",
    "Pasted image 20231209230057.png",
    "МАТЕМАТИЧЕСКИЙ АНАЛИЗ/Untitled.canvas"
  ]
}